tgcrypto.cpython-37m-darwin.so
tests/__init__.py
tests/cbc/__init__.py
tests/cbc/test_cbc.py
tests/ctr/__init__.py
tests/ctr/test_ctr.py
tests/ige/__init__.py
tests/ige/test_ige.py
TgCrypto-1.2.1.dist-info/COPYING
TgCrypto-1.2.1.dist-info/COPYING.lesser
TgCrypto-1.2.1.dist-info/METADATA
TgCrypto-1.2.1.dist-info/NOTICE
TgCrypto-1.2.1.dist-info/WHEEL
TgCrypto-1.2.1.dist-info/top_level.txt
TgCrypto-1.2.1.dist-info/RECORD
