Metadata-Version: 2.1
Name: TgCrypto
Version: 1.2.1
Summary: Fast Telegram Crypto Library for Python
Home-page: https://github.com/pyrogram
Author: Dan
Author-email: dan@pyrogram.org
License: LGPLv3+
Download-URL: https://github.com/pyrogram/tgcrypto/releases/latest
Project-URL: Documentation, https://docs.pyrogram.org
Project-URL: Community, https://t.me/pyrogram
Project-URL: Source, https://github.com/pyrogram/tgcrypto
Project-URL: Tracker, https://github.com/pyrogram/tgcrypto/issues
Keywords: fast pyrogram telegram crypto mtproto api client library python
Platform: UNKNOWN
Classifier: Development Status :: 5 - Production/Stable
Classifier: Intended Audience :: Developers
Classifier: License :: OSI Approved :: GNU Lesser General Public License v3 or later (LGPLv3+)
Classifier: Operating System :: OS Independent
Classifier: Programming Language :: C
Classifier: Programming Language :: Python
Classifier: Programming Language :: Python :: 3
Classifier: Programming Language :: Python :: 3.3
Classifier: Programming Language :: Python :: 3.4
Classifier: Programming Language :: Python :: 3.5
Classifier: Programming Language :: Python :: 3.6
Classifier: Programming Language :: Python :: 3.7
Classifier: Programming Language :: Python :: 3.8
Classifier: Programming Language :: Python :: Implementation
Classifier: Programming Language :: Python :: Implementation :: CPython
Classifier: Programming Language :: Python :: Implementation :: PyPy
Classifier: Topic :: Security
Classifier: Topic :: Security :: Cryptography
Classifier: Topic :: Internet
Classifier: Topic :: Communications
Classifier: Topic :: Communications :: Chat
Classifier: Topic :: Software Development :: Libraries
Classifier: Topic :: Software Development :: Libraries :: Python Modules
Requires-Python: ~=3.4
